.example.env
database/__init__.py
database/_connection.py
database/_entity.py
database/_model.py
database/_schema.py
database/shortcuts.py
tests/__init__.py
tests/conftest.py
tests/model.py
tests/test_entity.py
tests/test_smoke.py
pbt_database-1.3.2.dist-info/WHEEL
pbt_database-1.3.2.dist-info/METADATA
pbt_database-1.3.2.dist-info/RECORD
