Metadata-Version: 2.1
Name: pbt-database
Version: 1.3.2
Summary: Database driver
Author: everhide
Author-email: i.tolkachnikov@gmail.com
Requires-Python: >=3.9,<4.0
Classifier: Programming Language :: Python :: 3
Classifier: Programming Language :: Python :: 3.10
Classifier: Programming Language :: Python :: 3.9
Requires-Dist: SQLAlchemy (>=1.4.36,<2.0.0)
Requires-Dist: asyncpg (==0.25.0)
Requires-Dist: psycopg2-binary (==2.9.3)
